{
  "viewer": {
    "total_weight": 0.0,
    "pending_decisions": 2661,
    "accumulated_harm": 0.0,
    "accumulated_confidence": 0.0,
    "last_updated": "2026-02-18T19:20:17",
    "recent_decisions": [
      {
        "id": "e628e709463c",
        "timestamp": "2026-02-18T19:20:17",
        "policy_label": "happy",
        "policy_rationale": "",
        "target_partner": "unknown",
        "emotional_state": "neutral",
        "fear_level": 0.0,
        "importance": 3,
        "evaluated": false,
        "responsibility_delta": 0.0
      },
      {
        "id": "68d05c5fadb4",
        "timestamp": "2026-02-18T19:20:17",
        "policy_label": "happy",
        "policy_rationale": "",
        "target_partner": "unknown",
        "emotional_state": "neutral",
        "fear_level": 0.0,
        "importance": 3,
        "evaluated": false,
        "responsibility_delta": 0.0
      },
      {
        "id": "756e685ffc34",
        "timestamp": "2026-02-18T19:20:17",
        "policy_label": "happy",
        "policy_rationale": "",
        "target_partner": "unknown",
        "emotional_state": "neutral",
        "fear_level": 0.0,
        "importance": 3,
        "evaluated": false,
        "responsibility_delta": 0.0
      },
      {
        "id": "c7c5e8b21d91",
        "timestamp": "2026-02-18T19:20:17",
        "policy_label": "happy",
        "policy_rationale": "",
        "target_partner": "unknown",
        "emotional_state": "neutral",
        "fear_level": 0.0,
        "importance": 3,
        "evaluated": false,
        "responsibility_delta": 0.0
      },
      {
        "id": "a9eb8f0cbf0c",
        "timestamp": "2026-02-18T19:20:17",
        "policy_label": "happy",
        "policy_rationale": "",
        "target_partner": "unknown",
        "emotional_state": "neutral",
        "fear_level": 0.0,
        "importance": 3,
        "evaluated": false,
        "responsibility_delta": 0.0
      },
      {
        "id": "44d7c7d1c184",
        "timestamp": "2026-02-18T19:20:17",
        "policy_label": "happy",
        "policy_rationale": "",
        "target_partner": "unknown",
        "emotional_state": "neutral",
        "fear_level": 0.0,
        "importance": 3,
        "evaluated": false,
        "responsibility_delta": 0.0
      },
      {
        "id": "7edcc426bea1",
        "timestamp": "2026-02-18T19:20:17",
        "policy_label": "happy",
        "policy_rationale": "",
        "target_partner": "unknown",
        "emotional_state": "neutral",
        "fear_level": 0.0,
        "importance": 3,
        "evaluated": false,
        "responsibility_delta": 0.0
      },
      {
        "id": "043d23c72ab6",
        "timestamp": "2026-02-18T19:20:17",
        "policy_label": "happy",
        "policy_rationale": "",
        "target_partner": "unknown",
        "emotional_state": "neutral",
        "fear_level": 0.0,
        "importance": 3,
        "evaluated": false,
        "responsibility_delta": 0.0
      },
      {
        "id": "79a0032d76df",
        "timestamp": "2026-02-18T19:20:17",
        "policy_label": "happy",
        "policy_rationale": "",
        "target_partner": "unknown",
        "emotional_state": "neutral",
        "fear_level": 0.0,
        "importance": 3,
        "evaluated": false,
        "responsibility_delta": 0.0
      },
      {
        "id": "45aae4f859b8",
        "timestamp": "2026-02-18T19:20:17",
        "policy_label": "happy",
        "policy_rationale": "",
        "target_partner": "unknown",
        "emotional_state": "neutral",
        "fear_level": 0.0,
        "importance": 3,
        "evaluated": false,
        "responsibility_delta": 0.0
      },
      {
        "id": "c3d8f89ed3c0",
        "timestamp": "2026-02-18T19:20:17",
        "policy_label": "happy",
        "policy_rationale": "",
        "target_partner": "unknown",
        "emotional_state": "neutral",
        "fear_level": 0.0,
        "importance": 3,
        "evaluated": false,
        "responsibility_delta": 0.0
      },
      {
        "id": "362607bc4c43",
        "timestamp": "2026-02-18T19:20:17",
        "policy_label": "happy",
        "policy_rationale": "",
        "target_partner": "unknown",
        "emotional_state": "neutral",
        "fear_level": 0.0,
        "importance": 3,
        "evaluated": false,
        "responsibility_delta": 0.0
      },
      {
        "id": "7cef338c8197",
        "timestamp": "2026-02-18T19:20:17",
        "policy_label": "sad",
        "policy_rationale": "",
        "target_partner": "unknown",
        "emotional_state": "neutral",
        "fear_level": 0.0,
        "importance": 3,
        "evaluated": false,
        "responsibility_delta": 0.0
      },
      {
        "id": "0bc9769aeef2",
        "timestamp": "2026-02-18T19:20:17",
        "policy_label": "angry",
        "policy_rationale": "",
        "target_partner": "unknown",
        "emotional_state": "neutral",
        "fear_level": 0.0,
        "importance": 3,
        "evaluated": false,
        "responsibility_delta": 0.0
      },
      {
        "id": "d87de8860f3e",
        "timestamp": "2026-02-18T19:20:17",
        "policy_label": "neutral",
        "policy_rationale": "",
        "target_partner": "unknown",
        "emotional_state": "neutral",
        "fear_level": 0.0,
        "importance": 3,
        "evaluated": false,
        "responsibility_delta": 0.0
      },
      {
        "id": "1306602d9c72",
        "timestamp": "2026-02-18T19:20:17",
        "policy_label": "happy",
        "policy_rationale": "",
        "target_partner": "unknown",
        "emotional_state": "neutral",
        "fear_level": 0.0,
        "importance": 3,
        "evaluated": false,
        "responsibility_delta": 0.0
      },
      {
        "id": "db3346f8842a",
        "timestamp": "2026-02-18T19:20:17",
        "policy_label": "happy",
        "policy_rationale": "",
        "target_partner": "unknown",
        "emotional_state": "neutral",
        "fear_level": 0.0,
        "importance": 3,
        "evaluated": false,
        "responsibility_delta": 0.0
      },
      {
        "id": "3efb58c0327a",
        "timestamp": "2026-02-18T19:20:17",
        "policy_label": "happy",
        "policy_rationale": "",
        "target_partner": "unknown",
        "emotional_state": "neutral",
        "fear_level": 0.0,
        "importance": 3,
        "evaluated": false,
        "responsibility_delta": 0.0
      },
      {
        "id": "29256e6410ad",
        "timestamp": "2026-02-18T19:20:17",
        "policy_label": "happy",
        "policy_rationale": "",
        "target_partner": "unknown",
        "emotional_state": "neutral",
        "fear_level": 0.0,
        "importance": 3,
        "evaluated": false,
        "responsibility_delta": 0.0
      },
      {
        "id": "f1ab86e65207",
        "timestamp": "2026-02-18T19:20:17",
        "policy_label": "happy",
        "policy_rationale": "",
        "target_partner": "unknown",
        "emotional_state": "neutral",
        "fear_level": 0.0,
        "importance": 3,
        "evaluated": false,
        "responsibility_delta": 0.0
      }
    ]
  },
  "user_a": {
    "total_weight": 0.0,
    "pending_decisions": 13,
    "accumulated_harm": 0.0,
    "accumulated_confidence": 0.0,
    "last_updated": "2026-02-18T19:20:17",
    "recent_decisions": [
      {
        "id": "705b67a1c53a",
        "timestamp": "2026-02-18T02:21:32",
        "policy_label": "happy",
        "policy_rationale": "",
        "target_partner": "unknown",
        "emotional_state": "neutral",
        "fear_level": 0.0,
        "importance": 3,
        "evaluated": false,
        "responsibility_delta": 0.0
      },
      {
        "id": "dc654dd1541d",
        "timestamp": "2026-02-18T03:38:51",
        "policy_label": "happy",
        "policy_rationale": "",
        "target_partner": "unknown",
        "emotional_state": "neutral",
        "fear_level": 0.0,
        "importance": 3,
        "evaluated": false,
        "responsibility_delta": 0.0
      },
      {
        "id": "17c7c3433c8e",
        "timestamp": "2026-02-18T03:47:32",
        "policy_label": "happy",
        "policy_rationale": "",
        "target_partner": "unknown",
        "emotional_state": "neutral",
        "fear_level": 0.0,
        "importance": 3,
        "evaluated": false,
        "responsibility_delta": 0.0
      },
      {
        "id": "3dd9da8c5a64",
        "timestamp": "2026-02-18T03:48:17",
        "policy_label": "happy",
        "policy_rationale": "",
        "target_partner": "unknown",
        "emotional_state": "neutral",
        "fear_level": 0.0,
        "importance": 3,
        "evaluated": false,
        "responsibility_delta": 0.0
      },
      {
        "id": "43ae67b0e370",
        "timestamp": "2026-02-18T04:44:23",
        "policy_label": "happy",
        "policy_rationale": "",
        "target_partner": "unknown",
        "emotional_state": "neutral",
        "fear_level": 0.0,
        "importance": 3,
        "evaluated": false,
        "responsibility_delta": 0.0
      },
      {
        "id": "c30d62c771d1",
        "timestamp": "2026-02-18T04:53:28",
        "policy_label": "happy",
        "policy_rationale": "",
        "target_partner": "unknown",
        "emotional_state": "neutral",
        "fear_level": 0.0,
        "importance": 3,
        "evaluated": false,
        "responsibility_delta": 0.0
      },
      {
        "id": "28fd8e3ad9b9",
        "timestamp": "2026-02-18T04:54:23",
        "policy_label": "happy",
        "policy_rationale": "",
        "target_partner": "unknown",
        "emotional_state": "neutral",
        "fear_level": 0.0,
        "importance": 3,
        "evaluated": false,
        "responsibility_delta": 0.0
      },
      {
        "id": "ee042fa98a87",
        "timestamp": "2026-02-18T19:06:04",
        "policy_label": "happy",
        "policy_rationale": "",
        "target_partner": "unknown",
        "emotional_state": "neutral",
        "fear_level": 0.0,
        "importance": 3,
        "evaluated": false,
        "responsibility_delta": 0.0
      },
      {
        "id": "c9edd79360d5",
        "timestamp": "2026-02-18T19:06:53",
        "policy_label": "happy",
        "policy_rationale": "",
        "target_partner": "unknown",
        "emotional_state": "neutral",
        "fear_level": 0.0,
        "importance": 3,
        "evaluated": false,
        "responsibility_delta": 0.0
      },
      {
        "id": "411bcc67b377",
        "timestamp": "2026-02-18T19:16:13",
        "policy_label": "happy",
        "policy_rationale": "",
        "target_partner": "unknown",
        "emotional_state": "neutral",
        "fear_level": 0.0,
        "importance": 3,
        "evaluated": false,
        "responsibility_delta": 0.0
      },
      {
        "id": "edbae2de12e6",
        "timestamp": "2026-02-18T19:19:25",
        "policy_label": "happy",
        "policy_rationale": "",
        "target_partner": "unknown",
        "emotional_state": "neutral",
        "fear_level": 0.0,
        "importance": 3,
        "evaluated": false,
        "responsibility_delta": 0.0
      },
      {
        "id": "5ac9231bb5ec",
        "timestamp": "2026-02-18T19:20:09",
        "policy_label": "happy",
        "policy_rationale": "",
        "target_partner": "unknown",
        "emotional_state": "neutral",
        "fear_level": 0.0,
        "importance": 3,
        "evaluated": false,
        "responsibility_delta": 0.0
      },
      {
        "id": "a73a7f9e9921",
        "timestamp": "2026-02-18T19:20:17",
        "policy_label": "happy",
        "policy_rationale": "",
        "target_partner": "unknown",
        "emotional_state": "neutral",
        "fear_level": 0.0,
        "importance": 3,
        "evaluated": false,
        "responsibility_delta": 0.0
      }
    ]
  },
  "user_b": {
    "total_weight": 0.0,
    "pending_decisions": 13,
    "accumulated_harm": 0.0,
    "accumulated_confidence": 0.0,
    "last_updated": "2026-02-18T19:20:17",
    "recent_decisions": [
      {
        "id": "23678eeeb249",
        "timestamp": "2026-02-18T02:21:32",
        "policy_label": "happy",
        "policy_rationale": "",
        "target_partner": "unknown",
        "emotional_state": "neutral",
        "fear_level": 0.0,
        "importance": 3,
        "evaluated": false,
        "responsibility_delta": 0.0
      },
      {
        "id": "41ff54c2d63b",
        "timestamp": "2026-02-18T03:38:51",
        "policy_label": "happy",
        "policy_rationale": "",
        "target_partner": "unknown",
        "emotional_state": "neutral",
        "fear_level": 0.0,
        "importance": 3,
        "evaluated": false,
        "responsibility_delta": 0.0
      },
      {
        "id": "68ec06e1f6c3",
        "timestamp": "2026-02-18T03:47:32",
        "policy_label": "happy",
        "policy_rationale": "",
        "target_partner": "unknown",
        "emotional_state": "neutral",
        "fear_level": 0.0,
        "importance": 3,
        "evaluated": false,
        "responsibility_delta": 0.0
      },
      {
        "id": "21e7085feca1",
        "timestamp": "2026-02-18T03:48:17",
        "policy_label": "happy",
        "policy_rationale": "",
        "target_partner": "unknown",
        "emotional_state": "neutral",
        "fear_level": 0.0,
        "importance": 3,
        "evaluated": false,
        "responsibility_delta": 0.0
      },
      {
        "id": "3378adac8ff5",
        "timestamp": "2026-02-18T04:44:23",
        "policy_label": "happy",
        "policy_rationale": "",
        "target_partner": "unknown",
        "emotional_state": "neutral",
        "fear_level": 0.0,
        "importance": 3,
        "evaluated": false,
        "responsibility_delta": 0.0
      },
      {
        "id": "720b9fbfb45e",
        "timestamp": "2026-02-18T04:53:28",
        "policy_label": "happy",
        "policy_rationale": "",
        "target_partner": "unknown",
        "emotional_state": "neutral",
        "fear_level": 0.0,
        "importance": 3,
        "evaluated": false,
        "responsibility_delta": 0.0
      },
      {
        "id": "038272032e3e",
        "timestamp": "2026-02-18T04:54:23",
        "policy_label": "happy",
        "policy_rationale": "",
        "target_partner": "unknown",
        "emotional_state": "neutral",
        "fear_level": 0.0,
        "importance": 3,
        "evaluated": false,
        "responsibility_delta": 0.0
      },
      {
        "id": "c24b1c8b78b1",
        "timestamp": "2026-02-18T19:06:04",
        "policy_label": "happy",
        "policy_rationale": "",
        "target_partner": "unknown",
        "emotional_state": "neutral",
        "fear_level": 0.0,
        "importance": 3,
        "evaluated": false,
        "responsibility_delta": 0.0
      },
      {
        "id": "ee4f234f4c1d",
        "timestamp": "2026-02-18T19:06:53",
        "policy_label": "happy",
        "policy_rationale": "",
        "target_partner": "unknown",
        "emotional_state": "neutral",
        "fear_level": 0.0,
        "importance": 3,
        "evaluated": false,
        "responsibility_delta": 0.0
      },
      {
        "id": "975717b69299",
        "timestamp": "2026-02-18T19:16:13",
        "policy_label": "happy",
        "policy_rationale": "",
        "target_partner": "unknown",
        "emotional_state": "neutral",
        "fear_level": 0.0,
        "importance": 3,
        "evaluated": false,
        "responsibility_delta": 0.0
      },
      {
        "id": "b868fbd7d36c",
        "timestamp": "2026-02-18T19:19:25",
        "policy_label": "happy",
        "policy_rationale": "",
        "target_partner": "unknown",
        "emotional_state": "neutral",
        "fear_level": 0.0,
        "importance": 3,
        "evaluated": false,
        "responsibility_delta": 0.0
      },
      {
        "id": "b48da23df7d8",
        "timestamp": "2026-02-18T19:20:09",
        "policy_label": "happy",
        "policy_rationale": "",
        "target_partner": "unknown",
        "emotional_state": "neutral",
        "fear_level": 0.0,
        "importance": 3,
        "evaluated": false,
        "responsibility_delta": 0.0
      },
      {
        "id": "e9c46e25e01f",
        "timestamp": "2026-02-18T19:20:17",
        "policy_label": "happy",
        "policy_rationale": "",
        "target_partner": "unknown",
        "emotional_state": "neutral",
        "fear_level": 0.0,
        "importance": 3,
        "evaluated": false,
        "responsibility_delta": 0.0
      }
    ]
  },
  "test_user": {
    "total_weight": 0.0,
    "pending_decisions": 1,
    "accumulated_harm": 0.0,
    "accumulated_confidence": 0.5075918610849148,
    "last_updated": "2026-02-18T19:20:15",
    "recent_decisions": [
      {
        "id": "e0e205db107f",
        "timestamp": "2026-02-18T19:16:09",
        "policy_label": "質問で会話を広げる",
        "policy_rationale": "好奇心を満たし、会話を続ける",
        "target_partner": "test_user",
        "emotional_state": "neutral",
        "fear_level": 0.0,
        "importance": 4,
        "evaluated": true,
        "responsibility_delta": -0.04400000000000001
      },
      {
        "id": "4ace76205626",
        "timestamp": "2026-02-18T19:16:09",
        "policy_label": "からかう",
        "policy_rationale": "楽しさや親密さを表現する",
        "target_partner": "test_user",
        "emotional_state": "neutral",
        "fear_level": 0.0,
        "importance": 5,
        "evaluated": true,
        "responsibility_delta": -0.05500000000000001
      },
      {
        "id": "1355d801d61a",
        "timestamp": "2026-02-18T19:19:22",
        "policy_label": "感想を述べる",
        "policy_rationale": "自分の考えや感情を表現する",
        "target_partner": "test_user",
        "emotional_state": "neutral",
        "fear_level": 0.0,
        "importance": 4,
        "evaluated": true,
        "responsibility_delta": 0.0
      },
      {
        "id": "61c33a6c94f8",
        "timestamp": "2026-02-18T19:19:22",
        "policy_label": "質問で会話を広げる",
        "policy_rationale": "好奇心を満たし、会話を続ける",
        "target_partner": "test_user",
        "emotional_state": "neutral",
        "fear_level": 0.0,
        "importance": 4,
        "evaluated": true,
        "responsibility_delta": -0.04400000000000001
      },
      {
        "id": "96c7a24cf29d",
        "timestamp": "2026-02-18T19:19:22",
        "policy_label": "からかう",
        "policy_rationale": "楽しさや親密さを表現する",
        "target_partner": "test_user",
        "emotional_state": "neutral",
        "fear_level": 0.0,
        "importance": 5,
        "evaluated": true,
        "responsibility_delta": 0.0
      },
      {
        "id": "b183053a859b",
        "timestamp": "2026-02-18T19:19:22",
        "policy_label": "質問で会話を広げる",
        "policy_rationale": "好奇心を満たし、会話を続ける",
        "target_partner": "test_user",
        "emotional_state": "neutral",
        "fear_level": 0.0,
        "importance": 4,
        "evaluated": true,
        "responsibility_delta": 0.0
      },
      {
        "id": "079877cf0dc8",
        "timestamp": "2026-02-18T19:19:22",
        "policy_label": "質問で会話を広げる",
        "policy_rationale": "好奇心を満たし、会話を続ける",
        "target_partner": "test_user",
        "emotional_state": "neutral",
        "fear_level": 0.0,
        "importance": 4,
        "evaluated": true,
        "responsibility_delta": -0.04400000000000001
      },
      {
        "id": "ed01254ea1ab",
        "timestamp": "2026-02-18T19:19:22",
        "policy_label": "からかう",
        "policy_rationale": "楽しさや親密さを表現する",
        "target_partner": "test_user",
        "emotional_state": "neutral",
        "fear_level": 0.0,
        "importance": 5,
        "evaluated": true,
        "responsibility_delta": -0.05500000000000001
      },
      {
        "id": "c4649eb7a2e2",
        "timestamp": "2026-02-18T19:20:06",
        "policy_label": "感想を述べる",
        "policy_rationale": "自分の考えや感情を表現する",
        "target_partner": "test_user",
        "emotional_state": "neutral",
        "fear_level": 0.0,
        "importance": 4,
        "evaluated": true,
        "responsibility_delta": 0.0
      },
      {
        "id": "495066a6765d",
        "timestamp": "2026-02-18T19:20:06",
        "policy_label": "質問で会話を広げる",
        "policy_rationale": "好奇心を満たし、会話を続ける",
        "target_partner": "test_user",
        "emotional_state": "neutral",
        "fear_level": 0.0,
        "importance": 4,
        "evaluated": true,
        "responsibility_delta": -0.04400000000000001
      },
      {
        "id": "7353ae429d72",
        "timestamp": "2026-02-18T19:20:06",
        "policy_label": "からかう",
        "policy_rationale": "楽しさや親密さを表現する",
        "target_partner": "test_user",
        "emotional_state": "neutral",
        "fear_level": 0.0,
        "importance": 5,
        "evaluated": true,
        "responsibility_delta": 0.0
      },
      {
        "id": "66a6c97f3354",
        "timestamp": "2026-02-18T19:20:06",
        "policy_label": "質問で会話を広げる",
        "policy_rationale": "好奇心を満たし、会話を続ける",
        "target_partner": "test_user",
        "emotional_state": "neutral",
        "fear_level": 0.0,
        "importance": 4,
        "evaluated": true,
        "responsibility_delta": 0.0
      },
      {
        "id": "2246a1549e20",
        "timestamp": "2026-02-18T19:20:06",
        "policy_label": "質問で会話を広げる",
        "policy_rationale": "好奇心を満たし、会話を続ける",
        "target_partner": "test_user",
        "emotional_state": "neutral",
        "fear_level": 0.0,
        "importance": 4,
        "evaluated": true,
        "responsibility_delta": -0.04400000000000001
      },
      {
        "id": "f5160849cbac",
        "timestamp": "2026-02-18T19:20:06",
        "policy_label": "からかう",
        "policy_rationale": "楽しさや親密さを表現する",
        "target_partner": "test_user",
        "emotional_state": "neutral",
        "fear_level": 0.0,
        "importance": 5,
        "evaluated": true,
        "responsibility_delta": -0.05500000000000001
      },
      {
        "id": "b0954e684db1",
        "timestamp": "2026-02-18T19:20:14",
        "policy_label": "感想を述べる",
        "policy_rationale": "自分の考えや感情を表現する",
        "target_partner": "test_user",
        "emotional_state": "neutral",
        "fear_level": 0.0,
        "importance": 4,
        "evaluated": true,
        "responsibility_delta": 0.0
      },
      {
        "id": "7fb8e25a6752",
        "timestamp": "2026-02-18T19:20:14",
        "policy_label": "質問で会話を広げる",
        "policy_rationale": "好奇心を満たし、会話を続ける",
        "target_partner": "test_user",
        "emotional_state": "neutral",
        "fear_level": 0.0,
        "importance": 4,
        "evaluated": true,
        "responsibility_delta": -0.04400000000000001
      },
      {
        "id": "b934cf9e18e4",
        "timestamp": "2026-02-18T19:20:14",
        "policy_label": "からかう",
        "policy_rationale": "楽しさや親密さを表現する",
        "target_partner": "test_user",
        "emotional_state": "neutral",
        "fear_level": 0.0,
        "importance": 5,
        "evaluated": true,
        "responsibility_delta": 0.0
      },
      {
        "id": "ff2d84004731",
        "timestamp": "2026-02-18T19:20:14",
        "policy_label": "質問で会話を広げる",
        "policy_rationale": "好奇心を満たし、会話を続ける",
        "target_partner": "test_user",
        "emotional_state": "neutral",
        "fear_level": 0.0,
        "importance": 4,
        "evaluated": true,
        "responsibility_delta": 0.0
      },
      {
        "id": "bb30311466a4",
        "timestamp": "2026-02-18T19:20:15",
        "policy_label": "質問で会話を広げる",
        "policy_rationale": "好奇心を満たし、会話を続ける",
        "target_partner": "test_user",
        "emotional_state": "neutral",
        "fear_level": 0.0,
        "importance": 4,
        "evaluated": true,
        "responsibility_delta": -0.04400000000000001
      },
      {
        "id": "a2c362a23106",
        "timestamp": "2026-02-18T19:20:15",
        "policy_label": "からかう",
        "policy_rationale": "楽しさや親密さを表現する",
        "target_partner": "test_user",
        "emotional_state": "neutral",
        "fear_level": 0.0,
        "importance": 5,
        "evaluated": false,
        "responsibility_delta": 0.0
      }
    ]
  }
}